tamsismail/__init__.py
tamsismail/tamsismail.py
tamsismail-0.1.dist-info/LICENSE
tamsismail-0.1.dist-info/METADATA
tamsismail-0.1.dist-info/WHEEL
tamsismail-0.1.dist-info/top_level.txt
tamsismail-0.1.dist-info/RECORD
